timescale/__init__.py
timescale/eop.py
timescale/time.py
timescale/utilities.py
timescale/version.py
timescale/data/deltat.data
timescale/data/finals.all
timescale/data/historic_deltat.data
timescale/data/iers_deltat.data
timescale/data/leap-seconds.list
timescale/data/mean-pole.tab
timescale/data/merged_deltat.data
timescale/data/ser7.dat
timescale/data/tab5.2e.txt
timescale/data/tab5.3a.txt
timescale/data/tab5.3b.txt
timescale-0.1.0.dist-info/licenses/LICENSE
timescale-0.1.0.dist-info/METADATA
timescale-0.1.0.dist-info/WHEEL
timescale-0.1.0.dist-info/top_level.txt
timescale-0.1.0.dist-info/RECORD
