Metadata-Version: 2.4
Name: timescale
Version: 0.1.0
Summary: Python tools for time and astronomical calculations
Author: Tyler Sutterley, Karen Alley, Kelly Brunt, Susan Howard, Laurie Padman, Matt Siegfried
Author-email: tsutterl@uw.edu
Maintainer: timescale contributors
License: MIT License
Project-URL: Homepage, https://timescale.readthedocs.io
Project-URL: Documentation, https://timescale.readthedocs.io
Project-URL: Repository, https://github.com/pyTMD/timescale
Project-URL: Issues, https://github.com/pyTMD/timescale/issues
Keywords: Time,Leap Seconds,TAI,GPS,UT1,TT
Classifier: Development Status :: 3 - Alpha
Classifier: Intended Audience :: Science/Research
Classifier: License :: OSI Approved :: MIT License
Classifier: Operating System :: OS Independent
Classifier: Programming Language :: Python :: 3
Classifier: Programming Language :: Python :: 3.6
Classifier: Programming Language :: Python :: 3.7
Classifier: Programming Language :: Python :: 3.8
Classifier: Programming Language :: Python :: 3.9
Classifier: Programming Language :: Python :: 3.10
Classifier: Programming Language :: Python :: 3.11
Classifier: Programming Language :: Python :: 3.12
Classifier: Topic :: Scientific/Engineering :: Physics
Requires-Python: ~=3.6
License-File: LICENSE
Requires-Dist: lxml
Requires-Dist: numpy
Requires-Dist: python-dateutil
Requires-Dist: scipy>=1.10.1
Provides-Extra: doc
Requires-Dist: docutils; extra == "doc"
Requires-Dist: graphviz; extra == "doc"
Requires-Dist: myst-nb; extra == "doc"
Requires-Dist: numpydoc; extra == "doc"
Requires-Dist: sphinx; extra == "doc"
Requires-Dist: sphinx-argparse>=0.4; extra == "doc"
Requires-Dist: sphinxcontrib-bibtex; extra == "doc"
Requires-Dist: sphinx-design; extra == "doc"
Requires-Dist: sphinx_rtd_theme; extra == "doc"
Provides-Extra: dev
Requires-Dist: flake8; extra == "dev"
Requires-Dist: gh; extra == "dev"
Requires-Dist: pytest>=4.6; extra == "dev"
Requires-Dist: pytest-cov; extra == "dev"
Requires-Dist: pytest-xdist; extra == "dev"
Dynamic: license-file
